guardrails/__init__.py
guardrails/__main__.py
guardrails/guardrail_globals.py
guardrails/guardrails.py
guardrails/guardrails_log.py
guardrails-2.0.0.dist-info/LICENSE.md
guardrails-2.0.0.dist-info/METADATA
guardrails-2.0.0.dist-info/WHEEL
guardrails-2.0.0.dist-info/top_level.txt
guardrails-2.0.0.dist-info/RECORD
