Metadata-Version: 2.1
Name: guardrails
Version: 2.0.0
Summary: guardrails
Home-page: https://github.com/philips-software/python_guardrails
Author: Brijesh
Author-email: brijesh.krishnank@philips.com
License: UNKNOWN
Platform: UNKNOWN
Classifier: Programming Language :: Python :: 3
Classifier: License :: OSI Approved :: MIT License
Classifier: Operating System :: OS Independent
Requires-Python: >=3.8
